{
  "$schema": "https://raw.githubusercontent.com/badlogic/pi-mono/main/packages/coding-agent/src/modes/interactive/theme/theme-schema.json",
  "name": "pi-code",
  "vars": {
    "background": "#0f172a",
    "surface": "#1e293b",
    "surfaceAlt": "#334155",
    "foreground": "#e2e8f0",
    "muted": "#94a3b8",
    "border": "#334155",
    "primary": "#da7756",
    "primaryLight": "#e8956f",
    "primaryHover": "#c96842",
    "accent": "#6366f1",
    "indigo": "#818cf8",
    "dim": "#64748b",
    "faint": "#475569"
  },
  "colors": {
    "accent": "primary",
    "border": "faint",
    "borderAccent": "primary",
    "borderMuted": "faint",
    "success": "#10b981",
    "error": "#dc2626",
    "warning": "#f59e0b",
    "muted": "muted",
    "dim": "dim",
    "text": "foreground",
    "thinkingText": "muted",
    "selectedBg": "surface",
    "userMessageBg": "surface",
    "userMessageText": "foreground",
    "customMessageBg": "surface",
    "customMessageText": "foreground",
    "customMessageLabel": "primary",
    "toolPendingBg": "#1a2535",
    "toolSuccessBg": "#1a2e25",
    "toolErrorBg": "#2e1a1a",
    "toolTitle": "accent",
    "toolOutput": "foreground",
    "mdHeading": "primary",
    "mdLink": "accent",
    "mdLinkUrl": "dim",
    "mdCode": "#7dd3fc",
    "mdCodeBlock": "foreground",
    "mdCodeBlockBorder": "faint",
    "mdQuote": "muted",
    "mdQuoteBorder": "primary",
    "mdHr": "faint",
    "mdListBullet": "accent",
    "toolDiffAdded": "#22c55e",
    "toolDiffRemoved": "#ef4444",
    "toolDiffContext": "muted",
    "syntaxComment": "dim",
    "syntaxKeyword": "#c084fc",
    "syntaxFunction": "#7dd3fc",
    "syntaxVariable": "#fbbf24",
    "syntaxString": "#86efac",
    "syntaxNumber": "primary",
    "syntaxType": "#f0abfc",
    "syntaxOperator": "foreground",
    "syntaxPunctuation": "muted",
    "thinkingOff": "faint",
    "thinkingMinimal": "dim",
    "thinkingLow": "primary",
    "thinkingMedium": "accent",
    "thinkingHigh": "#8b5cf6",
    "thinkingXhigh": "#c084fc",
    "bashMode": "primary"
  },
  "export": {
    "pageBg": "#0f172a",
    "cardBg": "#1e293b",
    "infoBg": "#334155"
  }
}
